{
  "label": "nosh",
  "color": "#E8553A",
  "items": [
    {
      "id": "n1",
      "name": "オニオングリルハンバーグ",
      "cal": 382,
      "p": 17.2,
      "f": 24.6,
      "c": 20.5,
      "fi": 4.5,
      "cat": "meal",
      "meal": "lunch,dinner"
    },
    {
      "id": "n2",
      "name": "チリハンバーグステーキ",
      "cal": 368,
      "p": 15.2,
      "f": 23.3,
      "c": 21.9,
      "fi": 3.8,
      "cat": "meal",
      "meal": "lunch,dinner"
    },
    {
      "id": "n3",
      "name": "たらフライの特製タルタルソース",
      "cal": 467,
      "p": 19.1,
      "f": 31.5,
      "c": 22.2,
      "fi": 4.6,
      "cat": "meal",
      "meal": "lunch,dinner"
    },
    {
      "id": "n4",
      "name": "鶏もも肉の炭火焼き〜極〜",
      "cal": 266,
      "p": 17.4,
      "f": 16.6,
      "c": 8.7,
      "fi": 5.4,
      "cat": "meal",
      "meal": "lunch,dinner"
    },
    {
      "id": "n5",
      "name": "きのことチーズのトマトハンバーグ",
      "cal": 366,
      "p": 19.5,
      "f": 22.2,
      "c": 17.0,
      "fi": 6.0,
      "cat": "meal",
      "meal": "lunch,dinner"
    },
    {
      "id": "n6",
      "name": "チキンのトマトチーズがけ",
      "cal": 395,
      "p": 40.5,
      "f": 16.6,
      "c": 20.6,
      "fi": 4.1,
      "cat": "meal",
      "meal": "lunch,dinner"
    },
    {
      "id": "n7",
      "name": "白身魚の生姜醤油",
      "cal": 237,
      "p": 14.0,
      "f": 10.8,
      "c": 18.0,
      "fi": 3.6,
      "cat": "meal",
      "meal": "lunch,dinner"
    },
    {
      "id": "n8",
      "name": "ハンバーグと彩り温野菜のデミ",
      "cal": 362,
      "p": 17.0,
      "f": 21.1,
      "c": 20.2,
      "fi": 7.2,
      "cat": "meal",
      "meal": "lunch,dinner"
    },
    {
      "id": "n9",
      "name": "おろしソースのハンバーグ",
      "cal": 300,
      "p": 14.3,
      "f": 16.5,
      "c": 21.9,
      "fi": 5.5,
      "cat": "meal",
      "meal": "lunch,dinner"
    },
    {
      "id": "n10",
      "name": "たっぷり挽肉の麻婆茄子",
      "cal": 361,
      "p": 13.6,
      "f": 24.0,
      "c": 19.0,
      "fi": 5.5,
      "cat": "meal",
      "meal": "lunch,dinner"
    },
    {
      "id": "n11",
      "name": "コクと旨味のスイートチリカラアゲ",
      "cal": 393,
      "p": 24.1,
      "f": 19.6,
      "c": 29.2,
      "fi": 3.6,
      "cat": "meal",
      "meal": "lunch,dinner"
    },
    {
      "id": "n12",
      "name": "回鍋肉",
      "cal": 397,
      "p": 14.2,
      "f": 29.3,
      "c": 18.6,
      "fi": 3.8,
      "cat": "meal",
      "meal": "lunch,dinner"
    },
    {
      "id": "n13",
      "name": "旨だれペッパーチキン",
      "cal": 397,
      "p": 25.4,
      "f": 21.8,
      "c": 22.8,
      "fi": 4.6,
      "cat": "meal",
      "meal": "lunch,dinner"
    },
    {
      "id": "n14",
      "name": "ジョニーのからあげタルタルマシマシ！チキン南蛮",
      "cal": 385,
      "p": 34.5,
      "f": 16.3,
      "c": 22.3,
      "fi": 5.4,
      "cat": "meal",
      "meal": "lunch,dinner"
    },
    {
      "id": "n15",
      "name": "特製みそカツ",
      "cal": 288,
      "p": 13.9,
      "f": 11.7,
      "c": 29.5,
      "fi": 5.0,
      "cat": "meal",
      "meal": "lunch,dinner"
    },
    {
      "id": "n16",
      "name": "油淋鶏",
      "cal": 384,
      "p": 23.4,
      "f": 22.0,
      "c": 22.5,
      "fi": 3.5,
      "cat": "meal",
      "meal": "lunch,dinner"
    },
    {
      "id": "n17",
      "name": "鶏肉の照り焼き",
      "cal": 370,
      "p": 25.9,
      "f": 22.4,
      "c": 15.8,
      "fi": 3.4,
      "cat": "meal",
      "meal": "lunch,dinner"
    },
    {
      "id": "n18",
      "name": "クリームコロッケグラタン",
      "cal": 350,
      "p": 12.0,
      "f": 22.4,
      "c": 21.8,
      "fi": 5.3,
      "cat": "meal",
      "meal": "lunch,dinner"
    },
    {
      "id": "n19",
      "name": "にぎわい！中華づくし",
      "cal": 470,
      "p": 28.7,
      "f": 26.5,
      "c": 27.8,
      "fi": 3.6,
      "cat": "meal",
      "meal": "lunch,dinner"
    },
    {
      "id": "n20",
      "name": "海老満喫！チリディッシュ",
      "cal": 379,
      "p": 24.2,
      "f": 18.6,
      "c": 27.5,
      "fi": 3.4,
      "cat": "meal",
      "meal": "lunch,dinner"
    },
    {
      "id": "n21",
      "name": "ぷりっと海老の特製マヨソース",
      "cal": 414,
      "p": 19.1,
      "f": 25.1,
      "c": 24.4,
      "fi": 4.1,
      "cat": "meal",
      "meal": "lunch,dinner"
    },
    {
      "id": "n22",
      "name": "ザ・プレミアムハンバーグステーキ",
      "cal": 489,
      "p": 21.9,
      "f": 33.4,
      "c": 21.7,
      "fi": 4.2,
      "cat": "meal",
      "meal": "lunch,dinner"
    },
    {
      "id": "n23",
      "name": "うなぎの京風柳川仕立て",
      "cal": 300,
      "p": 18.1,
      "f": 17.0,
      "c": 15.0,
      "fi": 5.0,
      "cat": "meal",
      "meal": "lunch,dinner"
    },
    {
      "id": "n24",
      "name": "アンガスビーフのブラックカレー",
      "cal": 528,
      "p": 19.9,
      "f": 40.5,
      "c": 23.9,
      "fi": 5.4,
      "cat": "meal",
      "meal": "lunch,dinner"
    },
    {
      "id": "n25",
      "name": "海老クリームハンバーグ",
      "cal": 525,
      "p": 21.2,
      "f": 38.1,
      "c": 21.9,
      "fi": 3.7,
      "cat": "meal",
      "meal": "lunch,dinner"
    },
    {
      "id": "n26",
      "name": "銀鮭のマッシュポテトアヒージョ",
      "cal": 485,
      "p": 17.2,
      "f": 38.0,
      "c": 16.9,
      "fi": 4.0,
      "cat": "meal",
      "meal": "dinner"
    },
    {
      "id": "n27",
      "name": "うなぎのひつまぶし",
      "cal": 317,
      "p": 17.7,
      "f": 12.6,
      "c": 29.8,
      "fi": 3.0,
      "cat": "meal",
      "meal": "lunch,dinner"
    },
    {
      "id": "n28",
      "name": "ポルチーニ香る！銀鮭の具沢山クリーム仕立て",
      "cal": 336,
      "p": 21.6,
      "f": 22.5,
      "c": 10.4,
      "fi": 3.8,
      "cat": "meal",
      "meal": "dinner"
    },
    {
      "id": "n29",
      "name": "食いしん坊のための肉三昧",
      "cal": 565,
      "p": 37.4,
      "f": 41.9,
      "c": 10.5,
      "fi": 3.5,
      "cat": "meal",
      "meal": "lunch,dinner"
    },
    {
      "id": "n30",
      "name": "満腹御膳！具沢山そぼろの揚げ出し豆腐",
      "cal": 291,
      "p": 12.6,
      "f": 14.1,
      "c": 26.2,
      "fi": 4.9,
      "cat": "meal",
      "meal": "lunch,dinner"
    },
    {
      "id": "n31",
      "name": "豪快チキンのビリヤニライス",
      "cal": 459,
      "p": 24.2,
      "f": 25.3,
      "c": 28.7,
      "fi": 6.9,
      "cat": "meal",
      "meal": "lunch,dinner"
    },
    {
      "id": "n32",
      "name": "【増量】鶏もも肉の炭火焼き",
      "cal": 354,
      "p": 21.4,
      "f": 23.1,
      "c": 12.4,
      "fi": 4.7,
      "cat": "meal",
      "meal": "lunch,dinner"
    },
    {
      "id": "n33",
      "name": "【増量】オニオングリルハンバーグ",
      "cal": 549,
      "p": 27.5,
      "f": 36.7,
      "c": 24.3,
      "fi": 4.2,
      "cat": "meal",
      "meal": "lunch,dinner"
    },
    {
      "id": "n34",
      "name": "【増量】チリハンバーグステーキ",
      "cal": 542,
      "p": 25.3,
      "f": 36.1,
      "c": 26.5,
      "fi": 3.2,
      "cat": "meal",
      "meal": "lunch,dinner"
    },
    {
      "id": "n35",
      "name": "【増量】たっぷり挽肉の麻婆茄子",
      "cal": 445,
      "p": 19.1,
      "f": 31.4,
      "c": 17.9,
      "fi": 5.6,
      "cat": "meal",
      "meal": "lunch,dinner"
    },
    {
      "id": "n36",
      "name": "【増量】スタミナ焼肉",
      "cal": 669,
      "p": 27.0,
      "f": 53.9,
      "c": 21.4,
      "fi": 5.4,
      "cat": "meal",
      "meal": "lunch,dinner"
    },
    {
      "id": "n37",
      "name": "あとひく辛さ！麻婆ハンバーグめし",
      "cal": 266,
      "p": 13.3,
      "f": 10.3,
      "c": 27.7,
      "fi": 4.1,
      "cat": "meal",
      "meal": "lunch,dinner"
    },
    {
      "id": "n38",
      "name": "懐かしの和風チーズデミカツ",
      "cal": 391,
      "p": 17.7,
      "f": 21.5,
      "c": 28.3,
      "fi": 6.7,
      "cat": "meal",
      "meal": "lunch,dinner"
    },
    {
      "id": "n39",
      "name": "筍たっぷりチンジャオロース",
      "cal": 224,
      "p": 17.8,
      "f": 9.9,
      "c": 14.7,
      "fi": 3.0,
      "cat": "meal",
      "meal": "lunch,dinner"
    },
    {
      "id": "n40",
      "name": "旨味胡麻だれと彩り野菜のこんにゃく麺",
      "cal": 169,
      "p": 9.0,
      "f": 6.9,
      "c": 14.7,
      "fi": 5.1,
      "cat": "meal",
      "meal": "lunch"
    },
    {
      "id": "n41",
      "name": "ごま香る旨辛だれの牛肉チャプチェ",
      "cal": 379,
      "p": 14.0,
      "f": 28.5,
      "c": 15.3,
      "fi": 5.9,
      "cat": "meal",
      "meal": "lunch,dinner"
    },
    {
      "id": "n42",
      "name": "ゴロゴロ具沢山高菜チキンピラフ",
      "cal": 281,
      "p": 17.2,
      "f": 9.8,
      "c": 27.3,
      "fi": 4.1,
      "cat": "meal",
      "meal": "lunch,dinner"
    },
    {
      "id": "n43",
      "name": "黒胡椒香る牛肉の香味ソースあえ",
      "cal": 421,
      "p": 17.3,
      "f": 32.8,
      "c": 14.5,
      "fi": 4.9,
      "cat": "meal",
      "meal": "lunch,dinner"
    },
    {
      "id": "n44",
      "name": "バジル香る具沢山ミネストローネ",
      "cal": 212,
      "p": 9.2,
      "f": 9.9,
      "c": 19.1,
      "fi": 5.1,
      "cat": "soup",
      "meal": "lunch,dinner"
    },
    {
      "id": "n45",
      "name": "鶏肉の柚子胡椒〜極〜",
      "cal": 231,
      "p": 16.0,
      "f": 12.7,
      "c": 10.3,
      "fi": 4.8,
      "cat": "meal",
      "meal": "lunch,dinner"
    },
    {
      "id": "n46",
      "name": "白身魚とアサリのコンソメソース",
      "cal": 225,
      "p": 18.2,
      "f": 11.2,
      "c": 10.9,
      "fi": 3.2,
      "cat": "meal",
      "meal": "lunch,dinner"
    },
    {
      "id": "n47",
      "name": "白身魚のトマトクラムチャウダー",
      "cal": 218,
      "p": 20.0,
      "f": 8.5,
      "c": 11.7,
      "fi": 4.7,
      "cat": "meal",
      "meal": "lunch,dinner"
    },
    {
      "id": "n48",
      "name": "とろ〜りコンソメのロールキャベツ",
      "cal": 240,
      "p": 11.5,
      "f": 14.3,
      "c": 11.8,
      "fi": 6.2,
      "cat": "meal",
      "meal": "dinner"
    },
    {
      "id": "n49",
      "name": "鶏肉の爽やかねぎ塩だれ",
      "cal": 331,
      "p": 24.2,
      "f": 19.4,
      "c": 13.4,
      "fi": 3.5,
      "cat": "meal",
      "meal": "lunch,dinner"
    },
    {
      "id": "n50",
      "name": "とろ旨豚バラのカラフルベジソース",
      "cal": 577,
      "p": 17.5,
      "f": 49.2,
      "c": 13.9,
      "fi": 5.2,
      "cat": "meal",
      "meal": "dinner"
    },
    {
      "id": "n51",
      "name": "やさしいクリーミーソースオムレツ",
      "cal": 236,
      "p": 10.4,
      "f": 13.8,
      "c": 15.2,
      "fi": 5.1,
      "cat": "meal",
      "meal": "breakfast,lunch"
    },
    {
      "id": "n52",
      "name": "たっぷり野菜の旨辛プルコギ",
      "cal": 353,
      "p": 14.7,
      "f": 25.6,
      "c": 15.5,
      "fi": 4.9,
      "cat": "meal",
      "meal": "lunch,dinner"
    },
    {
      "id": "n53",
      "name": "ポークチリビーンズ",
      "cal": 434,
      "p": 18.4,
      "f": 33.2,
      "c": 15.6,
      "fi": 4.8,
      "cat": "meal",
      "meal": "lunch,dinner"
    },
    {
      "id": "n54",
      "name": "よだれ鶏",
      "cal": 457,
      "p": 23.5,
      "f": 31.7,
      "c": 15.8,
      "fi": 6.2,
      "cat": "meal",
      "meal": "lunch,dinner"
    },
    {
      "id": "n55",
      "name": "鯛つみれの生姜あん",
      "cal": 262,
      "p": 14.0,
      "f": 14.6,
      "c": 15.9,
      "fi": 5.1,
      "cat": "meal",
      "meal": "lunch,dinner"
    },
    {
      "id": "n56",
      "name": "豚バラ肉の爽やか梅仕立て",
      "cal": 385,
      "p": 14.9,
      "f": 29.2,
      "c": 16.2,
      "fi": 3.1,
      "cat": "meal",
      "meal": "lunch,dinner"
    },
    {
      "id": "n57",
      "name": "出汁香る筍と牛肉のあんかけ",
      "cal": 379,
      "p": 15.0,
      "f": 27.7,
      "c": 16.3,
      "fi": 4.8,
      "cat": "meal",
      "meal": "lunch,dinner"
    },
    {
      "id": "n58",
      "name": "なすと豚バラの甘辛中華だれ",
      "cal": 510,
      "p": 14.6,
      "f": 42.6,
      "c": 16.5,
      "fi": 3.2,
      "cat": "meal",
      "meal": "dinner"
    },
    {
      "id": "n59",
      "name": "たんぱく質チャージ！朝の麹チキン",
      "cal": 381,
      "p": 24.2,
      "f": 23.2,
      "c": 16.8,
      "fi": 4.2,
      "cat": "meal",
      "meal": "breakfast,lunch"
    },
    {
      "id": "n60",
      "name": "やさしいクリームリゾット",
      "cal": 277,
      "p": 18.4,
      "f": 13.5,
      "c": 17.2,
      "fi": 5.4,
      "cat": "meal",
      "meal": "lunch,dinner"
    },
    {
      "id": "n61",
      "name": "ピリッと辛い担々肉じゃが",
      "cal": 321,
      "p": 12.6,
      "f": 22.2,
      "c": 17.3,
      "fi": 4.6,
      "cat": "meal",
      "meal": "lunch,dinner"
    },
    {
      "id": "n62",
      "name": "豚バラ肉と野菜の甘辛ソースまみれ",
      "cal": 468,
      "p": 16.0,
      "f": 36.8,
      "c": 17.8,
      "fi": 3.8,
      "cat": "meal",
      "meal": "dinner"
    },
    {
      "id": "n63",
      "name": "ナッシュ流！豚バラの一口トンテキ",
      "cal": 422,
      "p": 16.9,
      "f": 31.0,
      "c": 17.8,
      "fi": 4.3,
      "cat": "meal",
      "meal": "lunch,dinner"
    },
    {
      "id": "n64",
      "name": "フライドフィッシュ",
      "cal": 431,
      "p": 17.7,
      "f": 29.6,
      "c": 20.0,
      "fi": 6.0,
      "cat": "meal",
      "meal": "lunch,dinner"
    },
    {
      "id": "n65",
      "name": "ハンバーグ＆チキンのガーリック",
      "cal": 347,
      "p": 21.4,
      "f": 19.3,
      "c": 20.6,
      "fi": 3.9,
      "cat": "meal",
      "meal": "lunch,dinner"
    },
    {
      "id": "n66",
      "name": "具沢山ボロネーゼのデリパスタ",
      "cal": 247,
      "p": 14.0,
      "f": 10.7,
      "c": 21.5,
      "fi": 4.7,
      "cat": "meal",
      "meal": "lunch,dinner"
    },
    {
      "id": "n67",
      "name": "お豆腐仕立ての和風ハンバーグ",
      "cal": 292,
      "p": 14.8,
      "f": 16.1,
      "c": 21.7,
      "fi": 3.7,
      "cat": "meal",
      "meal": "lunch,dinner"
    },
    {
      "id": "n68",
      "name": "CoCo壱番屋ハンバーグチーズのビーフカレー",
      "cal": 269,
      "p": 13.1,
      "f": 12.7,
      "c": 21.8,
      "fi": 5.2,
      "cat": "meal",
      "meal": "lunch,dinner"
    },
    {
      "id": "n69",
      "name": "たらのレモンあん",
      "cal": 272,
      "p": 17.4,
      "f": 12.3,
      "c": 22.0,
      "fi": 3.9,
      "cat": "meal",
      "meal": "lunch,dinner"
    },
    {
      "id": "n70",
      "name": "牛肉の旨辛スタミナクッパ",
      "cal": 386,
      "p": 17.4,
      "f": 24.3,
      "c": 23.0,
      "fi": 4.3,
      "cat": "meal",
      "meal": "lunch,dinner"
    },
    {
      "id": "n71",
      "name": "ほっこり鶏だし仕込みの中華粥",
      "cal": 211,
      "p": 16.5,
      "f": 4.6,
      "c": 23.7,
      "fi": 3.9,
      "cat": "meal",
      "meal": "breakfast,lunch"
    },
    {
      "id": "n72",
      "name": "にんにく醤油から揚げ",
      "cal": 375,
      "p": 24.7,
      "f": 19.9,
      "c": 23.8,
      "fi": 3.2,
      "cat": "meal",
      "meal": "lunch,dinner"
    },
    {
      "id": "n73",
      "name": "あんかけカツとじ",
      "cal": 283,
      "p": 13.5,
      "f": 13.7,
      "c": 24.2,
      "fi": 3.8,
      "cat": "meal",
      "meal": "lunch,dinner"
    },
    {
      "id": "n74",
      "name": "とろ～り半熟卵のトマトリゾット",
      "cal": 259,
      "p": 10.3,
      "f": 12.1,
      "c": 24.3,
      "fi": 4.1,
      "cat": "meal",
      "meal": "lunch,dinner"
    },
    {
      "id": "n75",
      "name": "たっぷり野菜と鯵の甘酢あん",
      "cal": 290,
      "p": 18.7,
      "f": 12.3,
      "c": 24.3,
      "fi": 3.1,
      "cat": "meal",
      "meal": "lunch,dinner"
    },
    {
      "id": "n76",
      "name": "あさりの旨味染み込む和のリゾット",
      "cal": 271,
      "p": 13.7,
      "f": 11.8,
      "c": 25.3,
      "fi": 3.0,
      "cat": "meal",
      "meal": "lunch,dinner"
    },
    {
      "id": "n77",
      "name": "特製ソースのマグロカツ",
      "cal": 315,
      "p": 17.4,
      "f": 14.2,
      "c": 26.6,
      "fi": 5.4,
      "cat": "meal",
      "meal": "lunch,dinner"
    },
    {
      "id": "n78",
      "name": "水餃子のチーズコチュジャン",
      "cal": 334,
      "p": 12.4,
      "f": 17.8,
      "c": 27.8,
      "fi": 4.8,
      "cat": "meal",
      "meal": "lunch,dinner"
    },
    {
      "id": "n79",
      "name": "たらの甘酢チリソース",
      "cal": 287,
      "p": 18.8,
      "f": 10.3,
      "c": 29.1,
      "fi": 3.5,
      "cat": "meal",
      "meal": "lunch,dinner"
    },
    {
      "id": "n80",
      "name": "チャーシュー炒飯",
      "cal": 323,
      "p": 11.6,
      "f": 15.8,
      "c": 29.7,
      "fi": 4.8,
      "cat": "meal",
      "meal": "lunch,dinner"
    },
    {
      "id": "n81",
      "name": "バンズパン(4個)",
      "cal": 92,
      "p": 8.4,
      "f": 4.4,
      "c": 2.1,
      "fi": 8.3,
      "cat": "bread",
      "meal": "breakfast"
    },
    {
      "id": "n82",
      "name": "バターロール(4個)",
      "cal": 91,
      "p": 7.6,
      "f": 3.7,
      "c": 4.5,
      "fi": 6.9,
      "cat": "bread",
      "meal": "breakfast"
    },
    {
      "id": "n83",
      "name": "チョコレートドーナツ(3個)",
      "cal": 155,
      "p": 2.9,
      "f": 9.2,
      "c": 13.4,
      "fi": 1.9,
      "cat": "dessert",
      "meal": "snack"
    },
    {
      "id": "n84",
      "name": "バナナドーナツ(3個)",
      "cal": 154,
      "p": 2.8,
      "f": 9.0,
      "c": 13.7,
      "fi": 1.9,
      "cat": "dessert",
      "meal": "snack"
    },
    {
      "id": "n85",
      "name": "チーズケーキバー(4本)",
      "cal": 177,
      "p": 3.5,
      "f": 12.0,
      "c": 12.4,
      "fi": 5.5,
      "cat": "dessert",
      "meal": "snack"
    },
    {
      "id": "n86",
      "name": "いちごミルキークリーム カップシフォン(3個)",
      "cal": 114,
      "p": 2.9,
      "f": 5.7,
      "c": 11.6,
      "fi": 1.9,
      "cat": "dessert",
      "meal": "snack"
    },
    {
      "id": "n87",
      "name": "ダブルチーズケーキ(2個)",
      "cal": 199,
      "p": 3.8,
      "f": 16.1,
      "c": 12.0,
      "fi": 0.5,
      "cat": "dessert",
      "meal": "snack"
    },
    {
      "id": "n88",
      "name": "カスタードミルキークリーム カップシフォン(3個)",
      "cal": 110,
      "p": 3.0,
      "f": 5.0,
      "c": 12.1,
      "fi": 1.9,
      "cat": "dessert",
      "meal": "snack"
    },
    {
      "id": "n89",
      "name": "ミルキークリーム カップシフォン(3個)",
      "cal": 114,
      "p": 3.0,
      "f": 5.4,
      "c": 12.1,
      "fi": 1.9,
      "cat": "dessert",
      "meal": "snack"
    },
    {
      "id": "n90",
      "name": "ティラミス(2個)",
      "cal": 176,
      "p": 3.0,
      "f": 13.5,
      "c": 13.1,
      "fi": 1.7,
      "cat": "dessert",
      "meal": "snack"
    },
    {
      "id": "n91",
      "name": "フォンダンショコラ(3個)",
      "cal": 175,
      "p": 2.7,
      "f": 13.0,
      "c": 14.7,
      "fi": 1.5,
      "cat": "dessert",
      "meal": "snack"
    },
    {
      "id": "n92",
      "name": "あんバターカステラ(2個)",
      "cal": 123,
      "p": 3.1,
      "f": 7.3,
      "c": 11.7,
      "fi": 4.2,
      "cat": "dessert",
      "meal": "snack"
    },
    {
      "id": "n93",
      "name": "レアチーズケーキ〜あまさけソース〜(3個)",
      "cal": 127,
      "p": 1.7,
      "f": 9.8,
      "c": 10.9,
      "fi": 0.6,
      "cat": "dessert",
      "meal": "snack"
    },
    {
      "id": "n94",
      "name": "レアチーズケーキ〜いちごソース〜(3個)",
      "cal": 124,
      "p": 1.7,
      "f": 10.0,
      "c": 10.3,
      "fi": 0.7,
      "cat": "dessert",
      "meal": "snack"
    }
  ]
}
